easygopigo3.py
gopigo3.py
I2C_mutex.py
mock_package/distance_sensor.py
mock_package/__init__.py
gopigo3-1.1.1.dist-info/WHEEL
gopigo3-1.1.1.dist-info/DESCRIPTION.rst
gopigo3-1.1.1.dist-info/metadata.json
gopigo3-1.1.1.dist-info/RECORD
gopigo3-1.1.1.dist-info/top_level.txt
gopigo3-1.1.1.dist-info/METADATA
Examples/Motor_Speed.py
Examples/easy_Motors.py
Examples/Grove_IR.py
Examples/Servo.py
Examples/Grove_LED.py
Examples/Motor_Position.py
Examples/Motor.py
Examples/Motor_Turn.py
Examples/Remote_Control.py
Examples/Grove_US2.py
Examples/easy_Light_Sensor.py
Examples/Grove_I2C.py
Examples/easy_Button.py
Examples/Motor_Follow.py
Examples/Grove_US.py
Examples/Grove_Buzzer.py
Examples/easy_LED.py
Examples/easy_Buzzer.py
Examples/easy_Blinkers.py
Examples/Motor_Encoder.py
Examples/easy_Distance_Sensor.py
Examples/LED.py
Examples/Read_Info.py
Examples/gps_reading.py
Examples/Grove_Light_Sensor.py
Examples/__init__.py
Examples/Grove.py
Examples/easy_DexEyes.py
Examples/Line_Sensor/line_sensor.py
Examples/Line_Sensor/basic_example.py
Examples/Line_Sensor/__init__.py
Examples/Line_Sensor/line_follower-basic_example.py
Examples/Control_Panel/control_panel_gui_3.py
Examples/Control_Panel/__init__.py
